ewatercycle_wflowjl/__init__.py
ewatercycle_wflowjl/model.py
ewatercycle_wflowjl/forcing/__init__.py
ewatercycle_wflowjl/forcing/diagnostic_script.py
ewatercycle_wflowjl/forcing/forcing.py
ewatercycle_wflowjl/forcing/makkink.py
ewatercycle_wflowjl-0.2.0.dist-info/METADATA
ewatercycle_wflowjl-0.2.0.dist-info/WHEEL
ewatercycle_wflowjl-0.2.0.dist-info/entry_points.txt
ewatercycle_wflowjl-0.2.0.dist-info/licenses/LICENSE.txt
ewatercycle_wflowjl-0.2.0.dist-info/RECORD
