Metadata-Version: 2.4
Name: ewatercycle-wflowjl
Version: 0.2.0
Summary: Wflow.jl eWaterCycle plugin
Author-email: "Bart Schilperoort, Peter Kalverla, Stefan Verhoeven" <b.schilperoort@esciencecenter.nl>
License-Expression: Apache-2.0
License-File: LICENSE.txt
Keywords: ewatercycle,hydrology
Classifier: Intended Audience :: Developers
Classifier: License :: OSI Approved :: Apache Software License
Classifier: Natural Language :: English
Classifier: Operating System :: OS Independent
Classifier: Programming Language :: Python
Classifier: Programming Language :: Python :: 3 :: Only
Requires-Dist: ewatercycle>=2.4.0
Requires-Dist: remotebmi
Requires-Dist: toml
Provides-Extra: dev
Requires-Dist: hatch; extra == 'dev'
Requires-Dist: ruff; extra == 'dev'
